[
  {
    "$type": "ModListMetadata, Wabbajack.Lib",
    "title": "Ghoulified Reality",
    "description": "A clean stable and beautiful 3BFTweaks Experience",
    "author": "Ghoulified",
    "maintainers": [
      "github/Ghoulified-Reality"
    ],
    "game": "skyrimspecialedition",
    "tags": [
      "Requiem",
      "3BFTweaks"
    ],
    "nsfw": false,
    "image_contains_title": false,
    "force_down": false,
    "links": {
      "$type": "Links, Wabbajack.Lib",
      "image": "https://raw.githubusercontent.com/Ghoulified/Ghoulified-Reality/main/Bigball.png",
      "readme": "https://themoddingbungalo.com/lists/ghoulified/index/",
      "download": "https://authored-files.wabbajack.org/Ghoulified%20Reality.wabbajack_d213cbad-7fb6-4a27-a71c-4839e500bbf4",
      "machineURL": "GhoulifiedReality",
      "discordURL": "https://discord.gg/BfUH6rUz"
    },
    "download_metadata": {
      "$type": "DownloadMetadata, Wabbajack.Lib",
      "Hash": "t309+6ooQRA=",
      "Size": 2074878927,
      "NumberOfArchives": 1733,
      "SizeOfArchives": 144426557116,
      "NumberOfInstalledFiles": 152337,
      "SizeOfInstalledFiles": 188003950083
    },
    "version": "1.6.7"
  }
]

