[
  {
    "$type": "ModListMetadata, Wabbajack.Lib",
    "title": "Ghoulified Reality",
    "description": "A clean stable and beautiful 3BFTweaks Experience",
    "author": "Ghoulified",
    "maintainers": [
      "github/Ghoulified-Reality"
    ],
    "game": "skyrimspecialedition",
    "tags": [
      "Requiem",
      "3BFTweaks"
    ],
    "nsfw": false,
    "image_contains_title": false,
    "force_down": false,
    "links": {
      "$type": "Links, Wabbajack.Lib",
      "image": "https://raw.githubusercontent.com/Ghoulified/Ghoulified-Reality/main/Bigball.png",
      "readme": "https://themoddingbungalo.com/lists/ghoulified/index/",
      "download": "https://authored-files.wabbajack.org/Ghoulified%20Reality.wabbajack_39424052-2b09-45b1-a0af-dbc58f7bb75e",
      "machineURL": "GhoulifiedReality",
      "discordURL": "https://discord.gg/BfUH6rUz"
    },
    "download_metadata": {
      "$type": "DownloadMetadata, Wabbajack.Lib",
      "Hash": "gsllnjTGwUM=",
      "Size": 2074568906,
      "NumberOfArchives": 1733,
      "SizeOfArchives": 144426557116,
      "NumberOfInstalledFiles": 152552,
      "SizeOfInstalledFiles": 188000877922
    },
    "version": "1.6.5"
  }
]

